py_logs_newrelic/__init__.py
py_logs_newrelic/push_logs.py
py_logs_newrelic-0.1.dist-info/METADATA
py_logs_newrelic-0.1.dist-info/WHEEL
py_logs_newrelic-0.1.dist-info/top_level.txt
py_logs_newrelic-0.1.dist-info/RECORD
