Metadata-Version: 2.1
Name: py-logs-newrelic
Version: 0.1
Summary: Un paquete para poder enviar mensajes a la api de new relic
Home-page: https://github.com/retmago/new_relic_api_python
Author: Jose Silva
Author-email: jsilva2018.95@gmail.com
License: UNKNOWN
Platform: UNKNOWN
Classifier: Programming Language :: Python :: 3
